README.md
setup.py
nido/__init__.py
nido.egg-info/PKG-INFO
nido.egg-info/SOURCES.txt
nido.egg-info/dependency_links.txt
nido.egg-info/not-zip-safe
nido.egg-info/requires.txt
nido.egg-info/top_level.txt
nido/lib/Adafruit_BME280.py
nido/lib/__init__.py
nido/lib/exceptions.py
nido/lib/Adafruit_GPIO/GPIO.py
nido/lib/Adafruit_GPIO/I2C.py
nido/lib/Adafruit_GPIO/Platform.py
nido/lib/Adafruit_GPIO/__init__.py
nido/lib/rpc/__init__.py
nido/lib/rpc/client.py
nido/lib/rpc/server.py
nido/supervisor/__init__.py
nido/supervisor/__main__.py
nido/supervisor/config.py
nido/supervisor/datalogger.py
nido/supervisor/db.py
nido/supervisor/hardware.py
nido/supervisor/simulator.py
nido/supervisor/thermostat.py
nido/web/__init__.py
nido/web/config.py
nido/web/api/__init__.py
nido/web/api/schedule.py
nido/web/api/thermostat.py