Metadata-Version: 2.1
Name: nido
Version: 1.0.3
Summary: Nido, a Raspberry Pi-based home thermostat
Home-page: https://github.com/alexmensch/nido-python
Author: Alex Marshall
Author-email: amars@alumni.stanford.edu
License: UNKNOWN
Platform: UNKNOWN
Classifier: Development Status :: 4 - Beta
Classifier: License :: OSI Approved :: GNU General Public License v3 or later (GPLv3+)
Classifier: Programming Language :: Python :: 3.6
Classifier: Programming Language :: Python :: 3.7
